objectify_json/__init__.py
objectify_json/__main__.py
objectify_json/formatter.py
objectify_json/obj_json.py
objectify_json/pure_eval.py
objectify_json-0.2.19.dist-info/METADATA
objectify_json-0.2.19.dist-info/WHEEL
objectify_json-0.2.19.dist-info/entry_points.txt
objectify_json-0.2.19.dist-info/top_level.txt
objectify_json-0.2.19.dist-info/RECORD
